Example.py
Url_encode.py
micropython_url_encode-0.1.dist-info/METADATA
micropython_url_encode-0.1.dist-info/WHEEL
micropython_url_encode-0.1.dist-info/licenses/LICENSE
micropython_url_encode-0.1.dist-info/RECORD
