Metadata-Version: 2.1
Name: micropython-url_encode
Version: 0.1
Summary: This is a micropython library aimed at encoding and decoding URLs.
Author: Sourav Nanda
Author-email: souravnanda41@gmail.com
Maintainer-email: Sourav Nanda <souravnanda41@gmail.com>
License: GNU GENERAL PUBLIC LICENSE
License-File: LICENSE
Keywords: Lobster Thermidor,bacon,egg,sausage,tomatoes
